bcmc/__init__.py
bcmc/__main__.py
bcmc/appsetup.py
bcmc/broadcast.py
bcmc/helpers.py
bcmc/multicast.py
bcmc/version.py
bcmc-0.1.0.post1.dist-info/LICENSE
bcmc-0.1.0.post1.dist-info/METADATA
bcmc-0.1.0.post1.dist-info/WHEEL
bcmc-0.1.0.post1.dist-info/entry_points.txt
bcmc-0.1.0.post1.dist-info/top_level.txt
bcmc-0.1.0.post1.dist-info/RECORD
