Metadata-Version: 2.1
Name: bcmc
Version: 0.1.0.post1
Summary: a CLI-centric broadcast and multicast validation tool
Author: Kevin L. Marshall
Author-email: Josh Schmelzle <josh@joshschmelzle.com>
Maintainer-email: Josh Schmelzle <josh@joshschmelzle.com>
License: BSD-3-Clause
Project-URL: Homepage, https://github.com/joshschmelzle/bcmc
Keywords: bcmc,broadcast,multicast
Classifier: Natural Language :: English
Classifier: Development Status :: 3 - Alpha
Classifier: Environment :: Console
Classifier: Programming Language :: Python :: 3
Classifier: Intended Audience :: Information Technology
Classifier: Intended Audience :: System Administrators
Classifier: Intended Audience :: Telecommunications Industry
Classifier: Topic :: Utilities
Classifier: Topic :: System :: Networking
Classifier: Topic :: System :: Networking :: Monitoring
Classifier: License :: OSI Approved :: BSD License
Requires-Python: >=3.9
License-File: LICENSE
